retrain/__init__.py
retrain/config_models.py
retrain/run.py
retrain-0.1.1.dist-info/METADATA
retrain-0.1.1.dist-info/WHEEL
retrain-0.1.1.dist-info/top_level.txt
retrain-0.1.1.dist-info/RECORD
