Metadata-Version: 2.4
Name: retrain
Version: 0.1.1
Summary: `retrain` is a Python library that uses Reinforcement Learning (RL) to help your Large Language Models (LLMs) learn new skills, master specific tasks, or follow complex instructions.
Requires-Python: >=3.12
Requires-Dist: fastmcp>=2.3.4
Requires-Dist: gymnasium>=1.1.1
Requires-Dist: loguru>=0.7.3
Requires-Dist: mcp>=1.8.1
Requires-Dist: peft>=0.15.2
Requires-Dist: pydantic>=2.11.4
Requires-Dist: pyyaml>=6.0.2
Requires-Dist: torch>=2.7.0
Requires-Dist: transformers>=4.51.3
Requires-Dist: trl>=0.17.0
Requires-Dist: unsloth>=2025.3.3
Requires-Dist: wandb>=0.19.11
